aioskybellgen/__init__.py
aioskybellgen/device.py
aioskybellgen/exceptions.py
aioskybellgen/py.typed
aioskybellgen/utils.py
aioskybellgen/helpers/__init__.py
aioskybellgen/helpers/const.py
aioskybellgen/helpers/errors.py
aioskybellgen/helpers/models.py
aioskybellgen-0.1.4.dist-info/METADATA
aioskybellgen-0.1.4.dist-info/WHEEL
aioskybellgen-0.1.4.dist-info/top_level.txt
aioskybellgen-0.1.4.dist-info/RECORD
