Metadata-Version: 2.4
Name: aioskybellgen
Version: 0.1.4
Summary: A Skybell Gen5 API Python library running on Python 3.
Author-email: Tim Carey <tlcareyintx@gmail.com>
Maintainer-email: Tim Carey <tlcareyintx@gmail.com>
License-Expression: MIT
Project-URL: Repository, https://github.com/tcareyintx/aioskybellgen.git
Project-URL: Bug Tracker, https://github.com/tcareyintx/aioskybellgen/issues
Keywords: aioskybellgen,skybellgen
Classifier: Development Status :: 4 - Beta
Classifier: Intended Audience :: Developers
Classifier: Natural Language :: English
Classifier: Operating System :: OS Independent
Classifier: Programming Language :: Python :: 3
Classifier: Programming Language :: Python :: 3.11
Classifier: Programming Language :: Python :: 3.12
Classifier: Programming Language :: Python :: 3.13
Classifier: Topic :: Software Development :: Libraries :: Python Modules
Requires-Python: >=3.11
Requires-Dist: aiofiles>=0.3.0
Requires-Dist: aiohttp<4.0,>=3.6.1
Requires-Dist: aresponses>=2.1.4
Requires-Dist: black>=21.11b1
Requires-Dist: build>=1.2.1
Requires-Dist: isort>=5.10.1
Requires-Dist: flake8>=4.0.1
Requires-Dist: flake8-docstrings>=1.6.0
Requires-Dist: freezegun>=1.5.1
Requires-Dist: mypy>=0.910
Requires-Dist: pylint>=2.12.1
Requires-Dist: pytest-cov>=3.0.0
Requires-Dist: pytest-asyncio>=0.16.0
Requires-Dist: pytest-freezer>=0.4.8
Requires-Dist: pytest>=6.2.4
Requires-Dist: types-aiofiles>=0.8.3
